callableabc/__init__.py
callableabc/callableabc.py
callableabc/py.typed
callableabc-2.1.0.dist-info/LICENSE
callableabc-2.1.0.dist-info/WHEEL
callableabc-2.1.0.dist-info/METADATA
callableabc-2.1.0.dist-info/RECORD
