Metadata-Version: 2.1
Name: callableabc
Version: 2.1.0
Summary: A variant of ABC that allows customizing the call behavior via _class_call()
Author-email: Anselm Schüler <mail@anselmschueler.com>
Requires-Python: >=3.10
Classifier: License :: OSI Approved :: Apache Software License
Project-URL: Home, https://github.com/schuelermine/callableabc
